pyface/__init__.py
pyface/about_dialog.py
pyface/api.py
pyface/application.py
pyface/application_window.py
pyface/array_image.py
pyface/base_toolkit.py
pyface/beep.py
pyface/clipboard.py
pyface/color.py
pyface/color_dialog.py
pyface/confirmation_dialog.py
pyface/constant.py
pyface/dialog.py
pyface/directory_dialog.py
pyface/drop_handler.py
pyface/expandable_panel.py
pyface/file_dialog.py
pyface/filter.py
pyface/font.py
pyface/font_dialog.py
pyface/gui.py
pyface/gui_application.py
pyface/heading_text.py
pyface/i_about_dialog.py
pyface/i_application_window.py
pyface/i_clipboard.py
pyface/i_color_dialog.py
pyface/i_confirmation_dialog.py
pyface/i_dialog.py
pyface/i_directory_dialog.py
pyface/i_drop_handler.py
pyface/i_file_dialog.py
pyface/i_font_dialog.py
pyface/i_gui.py
pyface/i_heading_text.py
pyface/i_image.py
pyface/i_image_cache.py
pyface/i_image_resource.py
pyface/i_layered_panel.py
pyface/i_layout_item.py
pyface/i_layout_widget.py
pyface/i_message_dialog.py
pyface/i_pil_image.py
pyface/i_progress_dialog.py
pyface/i_python_editor.py
pyface/i_python_shell.py
pyface/i_single_choice_dialog.py
pyface/i_splash_screen.py
pyface/i_split_widget.py
pyface/i_system_metrics.py
pyface/i_widget.py
pyface/i_window.py
pyface/image_cache.py
pyface/image_resource.py
pyface/image_widget.py
pyface/key_pressed_event.py
pyface/layered_panel.py
pyface/layout_widget.py
pyface/list_box.py
pyface/list_box_model.py
pyface/mdi_application_window.py
pyface/mdi_window_menu.py
pyface/message_dialog.py
pyface/mimedata.py
pyface/multi_toolbar_window.py
pyface/pil_image.py
pyface/progress_dialog.py
pyface/python_editor.py
pyface/python_shell.py
pyface/resource_manager.py
pyface/single_choice_dialog.py
pyface/sorter.py
pyface/splash_screen.py
pyface/splash_screen_log_handler.py
pyface/split_application_window.py
pyface/split_dialog.py
pyface/split_panel.py
pyface/split_widget.py
pyface/system_metrics.py
pyface/toolkit.py
pyface/ui_traits.py
pyface/widget.py
pyface/window.py
pyface-8.0.0.dist-info/LICENSE-CC-BY-3.0.txt
pyface-8.0.0.dist-info/LICENSE.txt
pyface-8.0.0.dist-info/METADATA
pyface-8.0.0.dist-info/WHEEL
pyface-8.0.0.dist-info/entry_points.txt
pyface-8.0.0.dist-info/top_level.txt
pyface-8.0.0.dist-info/RECORD
