Metadata-Version: 2.1
Name: pyface
Version: 8.0.0
Summary: Traits-capable windowing framework
Author-email: Enthought <info@enthought.com>
License: This software is OSI Certified Open Source Software.
Project-URL: source, https://github.com/enthought/pyface
Project-URL: docs, https://docs.enthought.com/pyface
Keywords: gui,traits,traitsui,pyqt,pyside,wxpython
Classifier: Development Status :: 5 - Production/Stable
Classifier: Intended Audience :: Developers
Classifier: License :: OSI Approved :: BSD License
Classifier: Operating System :: OS Independent
Classifier: Programming Language :: Python :: 3
Requires-Python: >=3.7
Provides-Extra: docs
Provides-Extra: examples
Provides-Extra: pillow
Provides-Extra: pyqt5
Provides-Extra: pyqt6
Provides-Extra: pyside2
Provides-Extra: pyside6
Provides-Extra: numpy
Provides-Extra: traitsui
Provides-Extra: test
Provides-Extra: wx
License-File: LICENSE-CC-BY-3.0.txt
License-File: LICENSE.txt
